logging_configurator/__init__.py
logging_configurator/core.py
logging_configurator/py.typed
logging_configurator-2.0.0.dist-info/METADATA
logging_configurator-2.0.0.dist-info/WHEEL
logging_configurator-2.0.0.dist-info/top_level.txt
logging_configurator-2.0.0.dist-info/RECORD
