Metadata-Version: 2.1
Name: logging_configurator
Version: 2.0.0
Summary: One-liner logging configurator for Python.
Home-page: https://github.com/Dmitrii-I/logging-configurator
Author: Dmitrii Izgurskii
Author-email: izgurskii@gmail.com
License: MIT
Keywords: logging
Requires-Python: >=3.7.0
